fastapi_tryton_connector/__init__.py
fastapi_tryton_connector/fastapi_tryton_connector.py
fastapi_tryton_connector-0.1.10.dist-info/LICENSE
fastapi_tryton_connector-0.1.10.dist-info/METADATA
fastapi_tryton_connector-0.1.10.dist-info/WHEEL
fastapi_tryton_connector-0.1.10.dist-info/RECORD
