Metadata-Version: 2.3
Name: fastapi_tryton_connector
Version: 0.1.10
Summary: A FastAPI extension for seamless integration with Tryton ERP.
License: GPL-3.0-or-later
Keywords: fastapi,tryton,erp,integration,python,connector
Author: Solutema SRL
Requires-Python: >=3.10,<4.0
Classifier: Environment :: Web Environment
Classifier: Framework :: FastAPI
Classifier: Framework :: Tryton
Classifier: Intended Audience :: Developers
Classifier: License :: OSI Approved :: GNU General Public License (GPL)
Classifier: License :: OSI Approved :: GNU General Public License v3 or later (GPLv3+)
Classifier: Operating System :: OS Independent
Classifier: Programming Language :: Python :: 3
Classifier: Programming Language :: Python :: 3.10
Classifier: Programming Language :: Python :: 3.11
Classifier: Programming Language :: Python :: 3.12
Classifier: Programming Language :: Python :: 3.13
Classifier: Topic :: Internet :: WWW/HTTP :: Dynamic Content
Classifier: Topic :: Software Development :: Libraries :: Python Modules
Requires-Dist: fastapi (>=0.115.12,<0.116.0)
Requires-Dist: proteus (>=6.0.0,<6.1.0)
Requires-Dist: psycopg2-binary (>=2.9.10,<3.0.0)
Requires-Dist: pydantic (>=2.11.5,<3.0.0)
Requires-Dist: pydantic-settings (>=2.9.1,<3.0.0)
Requires-Dist: trytond (>=6.0.0,<6.1.0)
Requires-Dist: uvicorn (>=0.34.3,<0.35.0)
